apmpython/__init__.py
apmpython/apmpython.py
apm_python_apm-0.1.4.dist-info/LICENSE
apm_python_apm-0.1.4.dist-info/METADATA
apm_python_apm-0.1.4.dist-info/WHEEL
apm_python_apm-0.1.4.dist-info/top_level.txt
apm_python_apm-0.1.4.dist-info/RECORD
