Metadata-Version: 2.1
Name: apm-python-apm
Version: 0.1.4
Summary: This package is use to check the RAM and CPU Usage of Current Device.
Home-page: https://github.com/middleware-labs/agent-apm-python.git
Author: test-author
License-File: LICENSE
